jit_utils/__init__.py
jit_utils/apiAuthSign.py
jit_utils/barcode.py
jit_utils/clsTool.py
jit_utils/convert.py
jit_utils/decorator.py
jit_utils/exceptions.py
jit_utils/forwarder.py
jit_utils/matchTool.py
jit_utils/network.py
jit_utils/qrcode.py
jit_utils/signature.py
jit_utils/spaceSender.py
jit_utils/string.py
jit_utils/time.py
jit_utils/validator.py
jit_utils/workday_constants.py
jit_utils/config/__init__.py
jit_utils/config/case.py
jit_utils/config/config.py
jit_utils/config/exception.py
jit_utils/config/field.py
jit_utils_backend-0.0.12.dist-info/METADATA
jit_utils_backend-0.0.12.dist-info/WHEEL
jit_utils_backend-0.0.12.dist-info/top_level.txt
jit_utils_backend-0.0.12.dist-info/RECORD
