Metadata-Version: 2.1
Name: jit_utils_backend
Version: 0.0.12
Summary: JIT Utils Backend
Author: JitAi
Author-email: support@jit.pro
Keywords: python,jit,sdk,apiAuth,utils,backend
Classifier: Development Status :: 3 - Alpha
Classifier: Intended Audience :: Developers
Classifier: Programming Language :: Python :: 3
Classifier: Programming Language :: Python :: 3.6
Classifier: Programming Language :: Python :: 3.7
Classifier: Programming Language :: Python :: 3.8
Classifier: Programming Language :: Python :: 3.9
Classifier: Programming Language :: Python :: 3.10
Classifier: Programming Language :: Python :: 3.11
Classifier: Operating System :: MacOS :: MacOS X
Classifier: Operating System :: Microsoft :: Windows
Classifier: Operating System :: POSIX :: Linux
Classifier: Topic :: Software Development :: Libraries :: Python Modules
Classifier: License :: OSI Approved :: MIT License
Requires-Python: >=3.6
Requires-Dist: requests
Requires-Dist: qrcode
Requires-Dist: python-barcode
Requires-Dist: Pillow
